flask_clearbit.py
setup.py
Flask_Clearbit.egg-info/PKG-INFO
Flask_Clearbit.egg-info/SOURCES.txt
Flask_Clearbit.egg-info/dependency_links.txt
Flask_Clearbit.egg-info/requires.txt
Flask_Clearbit.egg-info/top_level.txt
flask_clearbit.egg-info/PKG-INFO
flask_clearbit.egg-info/SOURCES.txt
flask_clearbit.egg-info/dependency_links.txt
flask_clearbit.egg-info/requires.txt
flask_clearbit.egg-info/top_level.txt