Metadata-Version: 1.0
Name: Flask-Clearbit
Version: 0.1.0
Summary: Flask-Clearbit
Home-page: https://github.com/raicheff/flask-clearbit
Author: Boris Raicheff
Author-email: b@raicheff.com
License: UNKNOWN
Platform: UNKNOWN
